request_id_logger/__init__.py
RequestIdLogger-0.1.dist-info/METADATA
RequestIdLogger-0.1.dist-info/WHEEL
RequestIdLogger-0.1.dist-info/top_level.txt
RequestIdLogger-0.1.dist-info/RECORD
